LICENSE
MANIFEST.in
README.rst
setup.py
Deployment/manage.py
DeploymentTool.egg-info/PKG-INFO
DeploymentTool.egg-info/SOURCES.txt
DeploymentTool.egg-info/dependency_links.txt
DeploymentTool.egg-info/requires.txt
DeploymentTool.egg-info/top_level.txt
Deployment/Deployment/__init__.py
Deployment/Deployment/__init__.pyc
Deployment/Deployment/settings.py
Deployment/Deployment/settings.pyc
Deployment/Deployment/urls.py
Deployment/Deployment/urls.pyc
Deployment/Deployment/wsgi.py
Deployment/Deployment/wsgi.pyc
Deployment/Deploymentapp/__init__.py
Deployment/Deploymentapp/__init__.pyc
Deployment/Deploymentapp/admin.py
Deployment/Deploymentapp/admin.pyc
Deployment/Deploymentapp/dobackup.py
Deployment/Deploymentapp/docopyfromtemp.py
Deployment/Deploymentapp/dodelbackup.py
Deployment/Deploymentapp/dodelproject.py
Deployment/Deploymentapp/dorollbacklog.py
Deployment/Deploymentapp/fabfile.py
Deployment/Deploymentapp/fabfile.pyc
Deployment/Deploymentapp/models.py
Deployment/Deploymentapp/models.pyc
Deployment/Deploymentapp/tests.py
Deployment/Deploymentapp/views.py
Deployment/Deploymentapp/views.pyc
Deployment/Static/Assets/css/bootstrap-theme.css
Deployment/Static/Assets/css/bootstrap-theme.css.map
Deployment/Static/Assets/css/bootstrap-theme.min.css
Deployment/Static/Assets/css/bootstrap.css
Deployment/Static/Assets/css/bootstrap.css.map
Deployment/Static/Assets/css/bootstrap.min.css
Deployment/Static/Assets/fonts/glyphicons-halflings-regular.eot
Deployment/Static/Assets/fonts/glyphicons-halflings-regular.svg
Deployment/Static/Assets/fonts/glyphicons-halflings-regular.ttf
Deployment/Static/Assets/fonts/glyphicons-halflings-regular.woff
Deployment/Static/Assets/js/bootstrap.js
Deployment/Static/Assets/js/bootstrap.min.js
Deployment/Static/Assets/js/jquery.min.js
Deployment/Static/admin/css/base.css
Deployment/Static/admin/css/changelists.css
Deployment/Static/admin/css/dashboard.css
Deployment/Static/admin/css/forms.css
Deployment/Static/admin/css/ie.css
Deployment/Static/admin/css/login.css
Deployment/Static/admin/css/rtl.css
Deployment/Static/admin/css/widgets.css
Deployment/Static/admin/img/changelist-bg.gif
Deployment/Static/admin/img/changelist-bg_rtl.gif
