Metadata-Version: 1.1
Name: DeploymentTool
Version: 1.5
Summary: Our deployment tool using django and fabric
Home-page: UNKNOWN
Author: Muhammad Irfan & Reza Adiyat
Author-email: muhammad.irfan92@gmail.com & rezaadiyat@gmail.com
License: BSD
Platform: UNKNOWN
Classifier: Environment :: Web Environment
Classifier: Framework :: Django
Classifier: Programming Language :: Python
Classifier: Programming Language :: Python :: 2.7
